<?xml version="1.0" encoding="utf-8" ?>
<dwsync>
<file name="1.png" server="170.10.162.251/shop.intermediacolombia.com/" local="131984355940000000" remote="134009307600000000" Dst="0" />
<file name="2.png" server="170.10.162.251/shop.intermediacolombia.com/" local="131984355940000000" remote="134009307600000000" Dst="0" />
<file name="3.png" server="170.10.162.251/shop.intermediacolombia.com/" local="131984355960000000" remote="134009307600000000" Dst="0" />
<file name="4.png" server="170.10.162.251/shop.intermediacolombia.com/" local="131984355960000000" remote="134009307600000000" Dst="0" />
<file name="5.png" server="170.10.162.251/shop.intermediacolombia.com/" local="131984355960000000" remote="134009307600000000" Dst="0" />
<file name="payments.webp" server="170.10.162.251/shop.intermediacolombia.com/" local="134030804994049905" remote="134030985600000000" Dst="0" />
<file name="1.png" server="capellb5.com/public_html/" local="131984355940000000" remote="134032347000000000" Dst="0" />
<file name="2.png" server="capellb5.com/public_html/" local="131984355940000000" remote="134032347000000000" Dst="0" />
<file name="4.png" server="capellb5.com/public_html/" local="131984355960000000" remote="134032347000000000" Dst="0" />
<file name="3.png" server="capellb5.com/public_html/" local="131984355960000000" remote="134032347000000000" Dst="0" />
<file name="5.png" server="capellb5.com/public_html/" local="131984355960000000" remote="134032347000000000" Dst="0" />
<file name="payments.webp" server="capellb5.com/public_html/" local="134030804994049905" remote="134032347000000000" Dst="0" />
</dwsync>