<?xml version="1.0" encoding="utf-8" ?>
<dwsync>
<file name="order_pay.php" server="170.10.164.133/shop.intermediacolombia.com/" local="134025654643280555" remote="134025834600000000" Dst="0" />
<file name="cron.php" server="170.10.164.133/shop.intermediacolombia.com/" local="134025657238697047" remote="134025845400000000" Dst="0" />
<file name="order_shipped.php" server="170.10.164.133/shop.intermediacolombia.com/" local="134025654918450171" remote="134025834600000000" Dst="0" />
<file name="order_delivered.php" server="170.10.164.133/shop.intermediacolombia.com/" local="134025677860204962" remote="134025857400000000" Dst="0" />
<file name="cron.php" server="capellb5.com/public_html/" local="134025657238697047" remote="134032346400000000" Dst="0" />
<file name="order_delivered.php" server="capellb5.com/public_html/" local="134025677860204962" remote="134032346400000000" Dst="0" />
<file name="order_shipped.php" server="capellb5.com/public_html/" local="134025654918450171" remote="134032346400000000" Dst="0" />
<file name="order_pay.php" server="capellb5.com/public_html/" local="134025654643280555" remote="134032346400000000" Dst="0" />
</dwsync>